[{"name": "ICIJ", "title": "International Finance Corporation watchdog in turmoil following scathing report on microfinance in Cambodia", "link": "https://www.icij.org/news/2026/07/international-finance-corporation-watchdog-in-turmoil-following-scathing-report-on-microfinance-in-cambodia/", "date": 1784135248000, "cat": "audit", "sig": 4}, {"name": "OCCRP", "title": "Graft, Gold, and Blackouts: Indonesia Prosecutes Its Own in $278 Million Coal Scandal", "link": "https://www.occrp.org/en/news/graft-gold-and-blackouts-indonesia-prosecutes-its-own-in-278-million-coal-scandal", "date": 1783971420000, "cat": "corruption", "sig": 8}, {"name": "OCCRP", "title": "Critics Slam Albania’s Emergency Bailout of Kanye West Concert as a $5 Million Smoke Screen", "link": "https://www.occrp.org/en/news/critics-slam-albanias-emergency-bailout-of-kanye-west-concert-as-a-5-million-smoke-screen", "date": 1783778340000, "cat": "banking", "sig": 9}, {"name": "OCCRP", "title": "$10 Million in a Storm Drain: Iraq Cracks Open 'Integrated Network' in Massive Oil Scandal", "link": "https://www.occrp.org/en/news/10-million-in-a-storm-drain-iraq-cracks-open-integrated-network-in-massive-oil-scandal", "date": 1783697220000, "cat": "corruption", "sig": 5}, {"name": "OCCRP", "title": "Millions in a Storm Drain: Iraq Cracks Open 'Integrated Network' in Massive Oil Scandal", "link": "https://www.occrp.org/en/news/millions-in-a-storm-drain-iraq-cracks-open-integrated-network-in-massive-oil-scandal", "date": 1783697220000, "cat": "corruption", "sig": 5}, {"name": "OCCRP", "title": "China: Former Official Sentenced to Death in $325 Million Bribery Case", "link": "https://www.occrp.org/en/news/china-former-official-sentenced-to-death-in-325-million-bribery-case", "date": 1783433640000, "cat": "corruption", "sig": 5}, {"name": "OCCRP", "title": "French Appeals Court Upholds Marine Le Pen’s Conviction but Clears Her to Run for Office", "link": "https://www.occrp.org/en/news/french-appeals-court-upholds-marine-le-pens-conviction-but-clears-her-to-run-for-office", "date": 1783431540000, "cat": "corruption", "sig": 5}, {"name": "Tax Justice Network", "title": "New Tax Justice Network reports on real estate transparency", "link": "https://taxjustice.net/2026/07/07/new-tax-justice-network-reports-on-real-estate-transparency/", "date": 1783414093000, "cat": "tax", "sig": 4}, {"name": "OCCRP", "title": "Iraq: PM Announces Rewards for Whistleblowers as Anti-Corruption Crackdown Widens", "link": "https://www.occrp.org/en/news/iraq-pm-announces-rewards-for-whistleblowers-as-anti-corruption-crackdown-widens", "date": 1783340040000, "cat": "corruption", "sig": 6}, {"name": "OCCRP", "title": "EU Prosecutor Raids Far-Right European Parliament Group Over Alleged Fraud", "link": "https://www.occrp.org/en/news/eu-prosecutor-raids-far-right-european-parliament-group-over-alleged-fraud", "date": 1782923220000, "cat": "corruption", "sig": 3}, {"name": "OCCRP", "title": "Bulgaria Detains 8 in EU Subsidy Fraud Probe", "link": "https://www.occrp.org/en/news/eppo-detains-8-in-bulgaria-eu-subsidy-fraud-probe", "date": 1782913260000, "cat": "corruption", "sig": 6}, {"name": "OCCRP", "title": "Iraq Intensifies Anti-Graft Drive with Dozens of High-Profile Arrests, Asset Seizures", "link": "https://www.occrp.org/en/news/iraq-intensifies-anti-graft-drive-with-dozens-of-high-profile-arrests-asset-seizures", "date": 1782892080000, "cat": "corruption", "sig": 5}, {"name": "The Lever", "title": "The Supreme Court Just Helped JD Vance Expand Citizens United", "link": "https://www.levernews.com/the-supreme-court-just-helped-j-d-vance-expand-citizens-united/", "date": 1782835095000, "cat": "corruption", "sig": 6}, {"name": "OCCRP", "title": "French Authorities Search Suspected VAT Fraud Network", "link": "https://www.occrp.org/en/news/french-authorities-search-suspected-vat-fraud-network", "date": 1782833400000, "cat": "corruption", "sig": 3}, {"name": "ProPublica", "title": "To Protect Its Drinking Water, This City Has to Appeal to the Oil Regulators That Put It at Risk", "link": "https://www.propublica.org/article/enid-oklahoma-oil-gas-pollution-water-protections", "date": 1782813600000, "cat": "banking", "sig": 3}, {"name": "Tax Justice Network", "title": "Four definitions to change the world: Struggles over meaning in the UN tax convention negotiations", "link": "https://taxjustice.net/2026/06/30/four-definitions-to-change-the-world-struggles-over-meaning-in-the-un-tax-convention-negotiations/", "date": 1782813456000, "cat": "international", "sig": 4}, {"name": "Tax Justice Network", "title": "Fiscal hell or mirage? What Spain’s wage debate gets wrong", "link": "https://taxjustice.net/2026/06/29/fiscal-hell-or-mirage-what-spains-wage-debate-gets-wrong/", "date": 1782758565000, "cat": "budgets", "sig": 4}, {"name": "OCCRP", "title": "Cabinet of the Blacklisted: Sanctioned Loyalists Take Charge of Venezuela’s Quake Relief", "link": "https://www.occrp.org/en/news/cabinet-of-the-blacklisted-sanctioned-loyalists-take-charge-of-venezuelas-quake-relief", "date": 1782745740000, "cat": "corruption", "sig": 3}, {"name": "OCCRP", "title": "German Court Sentences Black Market Banker to Nearly Four Years in Prison", "link": "https://www.occrp.org/en/news/german-court-sentences-black-market-banker", "date": 1782408540000, "cat": "corruption", "sig": 5}, {"name": "OCCRP", "title": "Philippines Arrest Senior Member of Japanese Fraud Syndicate", "link": "https://www.occrp.org/en/news/philippines-arrest-senior-member-of-japanese-fraud-syndicate", "date": 1782391200000, "cat": "corruption", "sig": 3}, {"name": "OCCRP", "title": "Ex-Cyprus President Slams Anti-Graft Report, Calls for Independent Probe", "link": "https://www.occrp.org/en/news/ex-cyprus-president-slams-anti-graft-report-calls-for-independent-probe", "date": 1782326400000, "cat": "corruption", "sig": 5}, {"name": "ICIJ", "title": "Law enforcement, banks warn of money laundering gaps in major US crypto bill", "link": "https://www.icij.org/investigations/coin-laundry/law-enforcement-banks-warn-of-money-laundering-gaps-in-major-us-crypto-bill/", "date": 1782307810000, "cat": "banking", "sig": 3}, {"name": "OCCRP", "title": "Iraq Recovers More Than $106 Million in Embezzled Cash, Some of It Buried", "link": "https://www.occrp.org/en/news/iraq-recovers-more-than-106-million-in-embezzled-cash-some-of-it-buried", "date": 1782305280000, "cat": "corruption", "sig": 8}, {"name": "OCCRP", "title": "Son of Late Gabonese Leader Bought Sprawling Real Estate Portfolio While in Public Office", "link": "https://www.occrp.org/en/project/openlux/son-of-late-gabonese-leader-bought-sprawling-real-estate-portfolio-while-in-public-office", "date": 1782273600000, "cat": "budgets", "sig": 5}, {"name": "ICIJ", "title": "Cyprus anti-corruption watchdog refers former president to prosecutors for alleged ‘abuse of power’", "link": "https://www.icij.org/investigations/pandora-papers/cyprus-anti-corruption-watchdog-refers-former-president-to-prosecutors-for-alleged-abuse-of-power/", "date": 1782246697000, "cat": "audit", "sig": 9}, {"name": "OCCRP", "title": "Nepal Court Orders Detention for Finance Minister Paudel in Money Laundering Probe", "link": "https://www.occrp.org/en/news/nepal-court-orders-detention-for-finance-minister-paudel-in-money-laundering-probe", "date": 1782237600000, "cat": "laundering", "sig": 5}, {"name": "OCCRP", "title": "US Slaps New Round of Sanctions on Cambodia’s Prince Group", "link": "https://www.occrp.org/en/news/us-slaps-second-package-of-sanctions-on-cambodias-prince-group", "date": 1782233400000, "cat": "international", "sig": 8}, {"name": "OCCRP", "title": "Syria Arrests Assad-Era Military Officer over Alleged Corruption and Wartime Abuses", "link": "https://www.occrp.org/en/news/syria-arrests-assad-era-military-officer-over-alleged-corruption-and-wartime-abuses", "date": 1782213120000, "cat": "corruption", "sig": 4}, {"name": "Tax Justice Network", "title": "Introducing the Real Estate Secrecy Index", "link": "https://taxjustice.net/2026/06/23/introducing-the-real-estate-secrecy-index/", "date": 1782169380000, "cat": "international", "sig": 3}, {"name": "Tax Justice Network", "title": "The European Court of Human Rights has upheld the weaponisation of privacy to restrict tax authorities’ access to banking data", "link": "https://taxjustice.net/2026/06/17/the-european-court-of-human-rights-has-upheld-the-weaponisation-of-privacy-to-restrict-tax-authorities-access-to-banking-data/", "date": 1781684279000, "cat": "tax", "sig": 6}, {"name": "Tax Justice Network", "title": "She cleans your house but the tax system can’t see her", "link": "https://taxjustice.net/2026/06/17/she-cleans-your-house-but-the-tax-system-cant-see-her/", "date": 1781680701000, "cat": "budgets", "sig": 4}, {"name": "Tax Justice Network", "title": "California steps up for tax fairness", "link": "https://taxjustice.net/2026/05/27/california-steps-up-for-tax-fairness/", "date": 1779871489000, "cat": "international", "sig": 3}, {"name": "Tax Justice Network", "title": "Finally, the European Court of Justice cracks down on trusts", "link": "https://taxjustice.net/2026/05/21/finally-the-european-court-of-justice-cracks-down-on-trusts/", "date": 1779376344000, "cat": "tax", "sig": 5}]